{
  "$schema": "https://mintlify.com/docs.json",
  "name": "MidOS",
  "theme": "aspen",
  "colors": {
    "primary": "#b1b1b1",
    "light": "#3c3c3c",
    "dark": "#e1e1e1"
  },
  "favicon": "/favicon.png",
  "logo": {
    "light": "/logo.png",
    "dark": "/logo.png"
  },
  "navbar": {
    "primary": {
      "type": "github",
      "href": "https://github.com/MidOSresearch/midos"
    }
  },
  "footer": {
    "socials": {
      "github": "https://github.com/MidOSresearch/midos",
      "website": "https://midos.dev"
    }
  },
  "navigation": {
    "tabs": [
      {
        "tab": "Documentation",
        "groups": [
          {
            "group": "Get Started",
            "pages": [
              "introduction",
              "quickstart",
              "installation"
            ]
          },
          {
            "group": "Core Concepts",
            "pages": [
              "concepts/knowledge-pipeline",
              "concepts/skill-packs",
              "concepts/eureka-system",
              "concepts/semantic-search"
            ]
          },
          {
            "group": "Guides",
            "pages": [
              "guides/connecting-to-mcp",
              "guides/search-strategies",
              "guides/using-skills",
              "guides/agent-handshake",
              "guides/self-hosting"
            ]
          },
          {
            "group": "Architecture",
            "pages": [
              "architecture/overview",
              "architecture/knowledge-layers",
              "architecture/vector-store",
              "architecture/authentication"
            ]
          }
        ]
      },
      {
        "tab": "API Reference",
        "groups": [
          {
            "group": "Overview",
            "pages": [
              "api/introduction",
              "api/authentication"
            ]
          },
          {
            "group": "Search Tools",
            "pages": [
              "api/search/search-knowledge",
              "api/search/semantic-search",
              "api/search/hybrid-search",
              "api/search/smart-search"
            ]
          },
          {
            "group": "Knowledge Tools",
            "pages": [
              "api/knowledge/get-skill",
              "api/knowledge/list-skills",
              "api/knowledge/get-eureka",
              "api/knowledge/get-truth",
              "api/knowledge/get-protocol"
            ]
          },
          {
            "group": "Agent Tools",
            "pages": [
              "api/agent/agent-handshake",
              "api/agent/episodic-search",
              "api/agent/episodic-store",
              "api/agent/chunk-code"
            ]
          },
          {
            "group": "System Tools",
            "pages": [
              "api/system/hive-status",
              "api/system/project-status",
              "api/system/memory-stats"
            ]
          }
        ]
      },
      {
        "tab": "Resources",
        "groups": [
          {
            "group": "Knowledge Base",
            "pages": [
              "resources/skill-catalog",
              "resources/eureka-catalog",
              "resources/truth-patches",
              "resources/tech-stacks"
            ]
          },
          {
            "group": "Community",
            "pages": [
              "contributing",
              "changelog",
              "faq"
            ]
          }
        ]
      }
    ]
  }
}
